castlebreaker/__init__.py
castlebreaker/client.py
castlebreaker/exceptions.py
castlebreaker/py.typed
castlebreaker/types.py
castlebreaker/services/__init__.py
castlebreaker/services/balance.py
castlebreaker/services/base.py
castlebreaker/services/castle.py
castlebreaker/services/recaptcha.py
castlebreaker/services/tls.py
castlebreaker/transport/__init__.py
castlebreaker/transport/async_.py
castlebreaker/transport/base.py
castlebreaker/transport/sync.py
castlebreaker-1.0.0.dist-info/METADATA
castlebreaker-1.0.0.dist-info/WHEEL
castlebreaker-1.0.0.dist-info/licenses/LICENSE
castlebreaker-1.0.0.dist-info/RECORD
