Metadata-Version: 2.4
Name: castlebreaker
Version: 1.0.0
Summary: Castle Breaker - Captcha solving service for Twitter/X account generation. Castle.io solver, ReCAPTCHA v3 bypass, TLS fingerprint bypass.
Project-URL: Homepage, https://castlebreaker.cc
Project-URL: Documentation, https://castlebreaker.cc/docs
Project-URL: Repository, https://github.com/castlebreaker/castlebreaker-python
Project-URL: Issues, https://github.com/castlebreaker/castlebreaker-python/issues
Author-email: Castle Breaker <support@castlebreaker.cc>
License-Expression: MIT
License-File: LICENSE
Keywords: automation,bot-detection,captcha,captcha-solver,castle,castle-io,castle-solver,cloudflare-bypass,recaptcha,recaptcha-solver,tls-bypass,twitter,twitter-account-generator,twitter-automation,twitter-gen,twitter-solver,x-account-generator,x-automation,x-gen,x-solver
Classifier: Development Status :: 5 - Production/Stable
Classifier: Intended Audience :: Developers
Classifier: License :: OSI Approved :: MIT License
Classifier: Operating System :: OS Independent
Classifier: Programming Language :: Python :: 3
Classifier: Programming Language :: Python :: 3.10
Classifier: Programming Language :: Python :: 3.11
Classifier: Programming Language :: Python :: 3.12
Classifier: Programming Language :: Python :: 3.13
Classifier: Topic :: Internet :: WWW/HTTP
Classifier: Topic :: Software Development :: Libraries :: Python Modules
Classifier: Typing :: Typed
Requires-Python: >=3.10
Requires-Dist: httpx>=0.27.0
Provides-Extra: dev
Requires-Dist: mypy>=1.10; extra == 'dev'
Requires-Dist: pytest-asyncio>=0.23; extra == 'dev'
Requires-Dist: pytest>=8.0; extra == 'dev'
Requires-Dist: ruff>=0.5.0; extra == 'dev'
